Jupyter_Video_Widget-0.3.1.data/data/share/jupyter/nbextensions/jupyter-video/extension.js
Jupyter_Video_Widget-0.3.1.data/data/share/jupyter/nbextensions/jupyter-video/index.js
Jupyter_Video_Widget-0.3.1.data/data/share/jupyter/nbextensions/jupyter-video/index.js.map
Jupyter_Video_Widget-0.3.1.dist-info/DESCRIPTION.rst
Jupyter_Video_Widget-0.3.1.dist-info/METADATA
Jupyter_Video_Widget-0.3.1.dist-info/RECORD
Jupyter_Video_Widget-0.3.1.dist-info/WHEEL
Jupyter_Video_Widget-0.3.1.dist-info/metadata.json
Jupyter_Video_Widget-0.3.1.dist-info/top_level.txt
jpy_video/__init__.py
jpy_video/_version.py
jpy_video/compound.py
jpy_video/monotext_widget.py
jpy_video/server.py
jpy_video/video.py
jpy_video/static/extension.js
jpy_video/static/index.js
jpy_video/static/index.js.map
