Metadata-Version: 2.0
Name: Jupyter-Video-Widget
Version: 0.3.1
Summary: A Jupyter HTML5 Video Player Widget
Home-page: https://github.com/Who8MyLunch/Jupyter_Video_Widget
Author: Pierre V. Villeneuve
Author-email: pierre.villeneuve@gmail.com
License: MIT
Keywords: ipython,jupyter,widgets,video,html5,player
Platform: Jupyter
Classifier: Development Status :: 4 - Beta
Classifier: Framework :: Jupyter
Classifier: Intended Audience :: Developers
Classifier: Intended Audience :: Science/Research
Classifier: Topic :: Multimedia :: Video
Classifier: Programming Language :: Python :: 3
Classifier: Programming Language :: Python :: 3.3
Classifier: Programming Language :: Python :: 3.4
Classifier: Programming Language :: Python :: 3.5
Classifier: Programming Language :: Python :: 3.6
Requires-Dist: ipython
Requires-Dist: jupyter
Requires-Dist: notebook
Requires-Dist: ipywidgets (>=7.0.0)
Requires-Dist: shortuuid
Requires-Dist: ordered-namespace
